{
  "$ref": "https://www.cert.ssi.gouv.fr/openapi.json",
  "affected_systems": [
    {
      "description": "Backup Exec 9.1.1152 for NetWare Servers ;",
      "product": {
        "name": "N/A",
        "vendor": {
          "name": "N/A",
          "scada": false
        }
      }
    },
    {
      "description": "Backup Exec 9.1.1152.4 for NetWare Servers ;",
      "product": {
        "name": "N/A",
        "vendor": {
          "name": "N/A",
          "scada": false
        }
      }
    },
    {
      "description": "Backup Exec 9.0.4202 for NetWare Servers ;",
      "product": {
        "name": "N/A",
        "vendor": {
          "name": "Microsoft",
          "scada": false
        }
      }
    },
    {
      "description": "Backup Exec 9.0.4174 for NetWare Servers ;",
      "product": {
        "name": "N/A",
        "vendor": {
          "name": "Microsoft",
          "scada": false
        }
      }
    },
    {
      "description": "Backup Exec 9.1.1154 for NetWare Servers ;",
      "product": {
        "name": "N/A",
        "vendor": {
          "name": "Microsoft",
          "scada": false
        }
      }
    },
    {
      "description": "Backup Exec 9.1.1127.1 for NetWare Servers ;",
      "product": {
        "name": "N/A",
        "vendor": {
          "name": "Microsoft",
          "scada": false
        }
      }
    },
    {
      "description": "Backup Exec 10.0 for Windows Servers rev. 5484 ;",
      "product": {
        "name": "Windows",
        "vendor": {
          "name": "Microsoft",
          "scada": false
        }
      }
    },
    {
      "description": "Backup Exec 9.0.4170 for NetWare Servers ;",
      "product": {
        "name": "N/A",
        "vendor": {
          "name": "Microsoft",
          "scada": false
        }
      }
    },
    {
      "description": "Backup Exec 10.0 for Windows Servers rev. 5520 ;",
      "product": {
        "name": "Windows",
        "vendor": {
          "name": "Microsoft",
          "scada": false
        }
      }
    },
    {
      "description": "Backup Exec 9.0 for Windows Servers rev. 4454 ;",
      "product": {
        "name": "Windows",
        "vendor": {
          "name": "Microsoft",
          "scada": false
        }
      }
    },
    {
      "description": "Backup Exec 9.0 for Windows Servers rev. 4367 ;",
      "product": {
        "name": "Windows",
        "vendor": {
          "name": "Microsoft",
          "scada": false
        }
      }
    },
    {
      "description": "Backup Exec 9.1.306 for NetWare Servers ;",
      "product": {
        "name": "N/A",
        "vendor": {
          "name": "Microsoft",
          "scada": false
        }
      }
    },
    {
      "description": "Backup Exec 9.1.1067.3 for NetWare Servers ;",
      "product": {
        "name": "N/A",
        "vendor": {
          "name": "Microsoft",
          "scada": false
        }
      }
    },
    {
      "description": "Backup Exec 9.0.4019 for NetWare Servers.",
      "product": {
        "name": "N/A",
        "vendor": {
          "name": "Microsoft",
          "scada": false
        }
      }
    },
    {
      "description": "Backup Exec 9.1.307 for NetWare Servers ;",
      "product": {
        "name": "N/A",
        "vendor": {
          "name": "Microsoft",
          "scada": false
        }
      }
    },
    {
      "description": "Backup Exec 9.1.1151.1 for NetWare Servers ;",
      "product": {
        "name": "N/A",
        "vendor": {
          "name": "Microsoft",
          "scada": false
        }
      }
    },
    {
      "description": "Backup Exec 9.1.1067.2 for NetWare Servers ;",
      "product": {
        "name": "N/A",
        "vendor": {
          "name": "Microsoft",
          "scada": false
        }
      }
    },
    {
      "description": "Backup Exec 9.1 for Windows Servers rev. 4691 ;",
      "product": {
        "name": "Windows",
        "vendor": {
          "name": "Microsoft",
          "scada": false
        }
      }
    },
    {
      "description": "Backup Exec 9.0.4172 for NetWare Servers ;",
      "product": {
        "name": "N/A",
        "vendor": {
          "name": "Microsoft",
          "scada": false
        }
      }
    }
  ],
  "affected_systems_content": null,
  "content": "## Description\n\nVeritas Backup Exec est un logiciel de sauvegarde.\n\nPlusieurs vulnérabilités affectent ce produit :\n\n-   deux vulnérabilités de type débordement de mémoire dans Veritas\n    Backup Exec Remote Agent permettent à un utilisateur mal intentionné\n    de réaliser un déni de service par arrêt brutal du serveur ;\n-   une vulnérabilité de type débordement de mémoire dans Veritas Backup\n    Exec Remote Agent for Windows Servers (RAWS) permet l'exécution de\n    code arbitraire à distance sur le serveur ;\n-   une vulnérabilité dans la validation des accès distants permet\n    l'obtention des privilèges de l'administrateur sur le registre du\n    serveur ;\n-   une vulnérabilité de type débordement de mémoire dans Backup Exec\n    Web Administration Console (BEWAC) permet l'exécution de code\n    arbitraire à distance sur le serveur ;\n-   une vulnérabilité dans Admin Plus Pack Option permet à un\n    utilisateur non autorisé d'obtenir un accès sur le serveur ;\n-   une vulnérabilité dans Veritas Backup Exec Remote Agent permet à un\n    utilisateur d'élever ses privilèges.\n\n## Solution\n\nAppliquer les correctifs indiqués dans le document 277429 de Veritas :\n\n    http://seer.support.veritas.com/docs/277429.htm\n",
  "cves": [],
  "links": [
    {
      "title": "Bulletin de sécurité Veritas VX05-006 du 22 juin 2005 :",
      "url": "http://seer.support.veritas.com/docs/276607.htm"
    },
    {
      "title": "Bulletin de sécurité Veritas VX05-007 du 22 juin 2005 :",
      "url": "http://seer.support.veritas.com/docs/276608.htm"
    },
    {
      "title": "Bulletin de sécurité Veritas VX05-002 du 22 juin 2005 :",
      "url": "http://seer.support.veritas.com/docs/276604.htm"
    },
    {
      "title": "Bulletin de sécurité Veritas VX05-005 du 22 juin 2005 :",
      "url": "http://seer.support.veritas.com/docs/276606.htm"
    },
    {
      "title": "Bulletin de sécurité Veritas VX05-001 du 22 juin 2005 :",
      "url": "http://seer.support.veritas.com/docs/276533.htm"
    },
    {
      "title": "Bulletin de sécurité Veritas VX05-003 du 22 juin 2005 :",
      "url": "http://seer.support.veritas.com/docs/276605.htm"
    }
  ],
  "reference": "CERTA-2005-AVI-229",
  "revisions": [
    {
      "description": "version initiale.",
      "revision_date": "2005-06-23T00:00:00.000000"
    }
  ],
  "risks": [
    {
      "description": "Accès non autorisé au système avec les privilèges de l'administrateur"
    },
    {
      "description": "Exécution de code arbitraire à distance"
    },
    {
      "description": "Déni de service"
    },
    {
      "description": "Élévation de privilèges"
    }
  ],
  "summary": "De multiples vulnérabilités affectant Veritas Backup Exec permettent\nl'exécution de code arbitraire à distance ou l'obtention d'un accès avec\nles privilèges de l'administrateur.\n",
  "title": "Multiples vulnérabilités de Veritas Backup Exec",
  "vendor_advisories": [
    {
      "published_at": null,
      "title": "VX05-005, VX05-006 et VX05-007 du 22 juin 2005",
      "url": null
    },
    {
      "published_at": null,
      "title": "Bulletins de sécurité Veritas VX05-001, VX05-002, VX05-003,",
      "url": null
    }
  ]
}