{
  "$ref": "https://www.cert.ssi.gouv.fr/openapi.json",
  "affected_systems": [],
  "affected_systems_content": "<P><SPAN class=\"textit\">WordPress</SPAN> versions 2.8.2 et  antérieures.</P>",
  "content": "## Description\n\nDe multiples vulnérabilités dans WordPress, décrites dans l'avis\nCERTA-2009-AVI-281 et permettant de réaliser une élévation de\nprivilèges, n'ont pas été correctement corrigées dans la version 2.8.1.\n\n## Solution\n\nSe référer au bulletin de sécurité de l'éditeur pour l'obtention des\ncorrectifs (cf. section Documentation).\n",
  "cves": [],
  "links": [
    {
      "title": "Notes de version 2.8.3 de WordPress :",
      "url": "http://wordpress.org/development/2009/08/wordpress-2-8-3-security-release/"
    }
  ],
  "reference": "CERTA-2009-AVI-315",
  "revisions": [
    {
      "description": "version initiale.",
      "revision_date": "2009-08-07T00:00:00.000000"
    }
  ],
  "risks": [
    {
      "description": "Élévation de privilèges"
    }
  ],
  "summary": "De multiples vulnérabilités dans <span class=\"textit\">WordPress</span>\npermettent de réaliser une élévation de privilèges.\n",
  "title": "Multiples vulnérabilités dans WordPress",
  "vendor_advisories": [
    {
      "published_at": null,
      "title": "Notes de version 2.8.3 de WordPress du 03 août 2009",
      "url": null
    }
  ]
}