{
  "$ref": "https://www.cert.ssi.gouv.fr/openapi.json",
  "affected_systems": [],
  "affected_systems_content": "<p>Les versions de WordPress antérieures à  la 2.8.2.</p>",
  "content": "## Description\n\nUne vulnérabilité concernant un défaut de validation des paramètres lors\nde l'écriture d'un commentaire sur WordPress a été corrigée. Elle permet\nà une personne malveillante de conduire une attaque en XSS au moyen d'un\ncommentaire spécifiquement écrit.\n\n## Solution\n\nSe référer au bulletin de sécurité de l'éditeur pour l'obtention des\ncorrectifs (cf. section Documentation).\n",
  "cves": [],
  "links": [],
  "reference": "CERTA-2009-AVI-287",
  "revisions": [
    {
      "description": "version initiale.",
      "revision_date": "2009-07-22T00:00:00.000000"
    }
  ],
  "risks": [
    {
      "description": "Injection de code indirecte"
    }
  ],
  "summary": "Une vulnérabilité permettant l'injection de code indirecte (XSS) a été\ncorrigée.\n",
  "title": "Vulnérabilité dans WordPress",
  "vendor_advisories": [
    {
      "published_at": null,
      "title": "Bulletin de sécurité WordPress 2.8.2 du 20 juillet 2009",
      "url": "http://wordpress.org/development/2009/07/wordpress-2-8-2/"
    }
  ]
}