{
  "$ref": "https://www.cert.ssi.gouv.fr/openapi.json",
  "affected_systems": [
    {
      "description": "Ubuntu version 6.06 LTS ;",
      "product": {
        "name": "Ubuntu",
        "vendor": {
          "name": "Ubuntu",
          "scada": false
        }
      }
    },
    {
      "description": "Ubuntu version 7.10 ;",
      "product": {
        "name": "Ubuntu",
        "vendor": {
          "name": "Ubuntu",
          "scada": false
        }
      }
    },
    {
      "description": "Ubuntu version 8.04 LTS ;",
      "product": {
        "name": "Ubuntu",
        "vendor": {
          "name": "Ubuntu",
          "scada": false
        }
      }
    },
    {
      "description": "Ubuntu version 8.10.",
      "product": {
        "name": "Ubuntu",
        "vendor": {
          "name": "Ubuntu",
          "scada": false
        }
      }
    }
  ],
  "affected_systems_content": null,
  "content": "## Description\n\nUn défaut d'avertissement dans KMail lors du suivi d'un lien vers un\nfichier exécutable permet à un individu malveillant de contourner la\npolitique de sécurité par le biais d'un courriel au format HTML\nspécialement construit.\n\nLe CERTA rappelle que la lecture au format HTML des courriers\nélectroniques n'est pas recommandée.\n\n## Solution\n\nSe référer au bulletin de sécurité de l'éditeur pour l'obtention des\ncorrectifs (cf. section Documentation).\n",
  "cves": [],
  "links": [],
  "reference": "CERTA-2009-AVI-106",
  "revisions": [
    {
      "description": "version initiale.",
      "revision_date": "2009-03-18T00:00:00.000000"
    }
  ],
  "risks": [
    {
      "description": "Contournement de la politique de sécurité"
    }
  ],
  "summary": "Une vulnérabilité de <span class=\"textit\">KMail</span> permet à un\nindividu malveillant de contourner la politique de sécurité.\n",
  "title": "Vulnérabilité dans KMail",
  "vendor_advisories": [
    {
      "published_at": null,
      "title": "Bulletin de sécurité Ubuntu USN-725-1 du 26 février 2009",
      "url": "http://www.ubuntulinux.org/usn/usn-725-1"
    }
  ]
}