{
  "$ref": "https://www.cert.ssi.gouv.fr/openapi.json",
  "affected_systems": [
    {
      "description": "Novell Apache on Netware 2.0.48.",
      "product": {
        "name": "N/A",
        "vendor": {
          "name": "N/A",
          "scada": false
        }
      }
    },
    {
      "description": "Novell Netware 6.5 Support Pack 5 ;",
      "product": {
        "name": "N/A",
        "vendor": {
          "name": "Novell",
          "scada": false
        }
      }
    },
    {
      "description": "Novell Netware 6.5 Support Pack 7 ;",
      "product": {
        "name": "N/A",
        "vendor": {
          "name": "Novell",
          "scada": false
        }
      }
    },
    {
      "description": "Novell Netware 6.5 Support Pack 6 ;",
      "product": {
        "name": "N/A",
        "vendor": {
          "name": "Novell",
          "scada": false
        }
      }
    }
  ],
  "affected_systems_content": null,
  "content": "## Description\n\nUne vulnérabilité permet à une personne malintentionnée d'accéder, sans\nmot de passe, à la console ApacheAdmin après l'installation du serveur\nLinux OES2 sur Netware 6.5.\n\nGénéralement, ce problème survient lorsque le serveur Netware a été mis\nà jour à partir d'une version précédente de Netware 6.5 (i.e. Support\nPack 2 à 7).\n\n## Solution\n\nSe référer au bulletin de sécurité de l'éditeur pour l'obtention des\ncorrectifs (cf. section Documentation).\n",
  "cves": [],
  "links": [],
  "reference": "CERTA-2008-AVI-582",
  "revisions": [
    {
      "description": "version initiale.",
      "revision_date": "2008-12-08T00:00:00.000000"
    }
  ],
  "risks": [
    {
      "description": "Contournement de la politique de sécurité"
    }
  ],
  "summary": "Une vulnérabilité découverte dans Apache pour Novell Netware permet à\nune personne malintentionnée de contourner la politique de sécurité.\n",
  "title": "Vulnérabilité dans Apache pour Novell Netware",
  "vendor_advisories": [
    {
      "published_at": null,
      "title": "Bulletin de sécurité Novell #7001907 du 04 décembre 2008",
      "url": "http://www.novell.com/support/viewContent.do?externalId=7001907"
    }
  ]
}