{
  "$ref": "https://www.cert.ssi.gouv.fr/openapi.json",
  "affected_systems": [],
  "affected_systems_content": "<p>Les versions de Nagios antérieures à la  3.0.5.</p>",
  "content": "## Description\n\nUn attaquant peut conduire un utilisateur à effectuer des opérations\nNagios malgré lui en l'incitant à consulter du code HTML spécifiquement\nécrit. Pour cela, l'utilisateur doit être connecté à l'interface Nagios\nlors de la consultation du code malveillant.\n\n## Solution\n\nSe référer au bulletin de sécurité de l'éditeur pour l'obtention des\ncorrectifs (cf. section Documentation).\n",
  "cves": [],
  "links": [],
  "reference": "CERTA-2008-AVI-545",
  "revisions": [
    {
      "description": "version initiale.",
      "revision_date": "2008-11-06T00:00:00.000000"
    }
  ],
  "risks": [
    {
      "description": "Injection de requêtes illégitimes par rebond (CSRF)"
    }
  ],
  "summary": "Un défaut de contrôle de validité des requêtes entrainant une\nvulnérabilité de type <span class=\"textit\">CSRF</span> (<span\nclass=\"textit\">Cross Site Request Forgery</span>) a été corrigé.\n",
  "title": "Vulnérabilité dans Nagios",
  "vendor_advisories": [
    {
      "published_at": null,
      "title": "Bulletin de mise à jour Nagios 3.0.5 du 4 novembre 2008",
      "url": "http://www.nagios.org/development/history/nagios-3x.php"
    }
  ]
}