{
  "$ref": "https://www.cert.ssi.gouv.fr/openapi.json",
  "affected_systems": [
    {
      "description": "Les moteurs antérieurs à 1.0.173 de CA Personal Firewall 2007 9.0 sur Microsoft Windows ;",
      "product": {
        "name": "Windows",
        "vendor": {
          "name": "Microsoft",
          "scada": false
        }
      }
    },
    {
      "description": "les moteurs antérieurs à 1.0.173 de CA Personal Firewall 2007 dans CA Internet Security Suite 2007 sur Microsoft Windows.",
      "product": {
        "name": "N/A",
        "vendor": {
          "name": "Microsoft",
          "scada": false
        }
      }
    }
  ],
  "affected_systems_content": null,
  "content": "## Description\n\nPlusieurs vulnérabilités sur CA Personal Firewall 2007 permettraient à\nune personne malintentionnée d'effectuer une élévation de privilèges.\nLes vulnérabilités sont dues à des erreurs dans les pilotes KmxStart.sys\net KmxFw.sys.\n\n## Solution\n\nUne mise à jour automatique qui corrige ces vulnérabilités est\ndisponible depuis le 22 janvier 2007.\n",
  "cves": [],
  "links": [
    {
      "title": "Bulletin de sécurité de CA :",
      "url": "http://www3.ca.com/securityadvisor/newsinfo/collateral.aspx?cid=97729"
    }
  ],
  "reference": "CERTA-2007-AVI-058",
  "revisions": [
    {
      "description": "version initiale.",
      "revision_date": "2007-01-26T00:00:00.000000"
    }
  ],
  "risks": [
    {
      "description": "Élévation de privilèges"
    }
  ],
  "summary": "De multiples vulnérabilités sur <span class=\"textit\">CA Personal\nFirewall 2007</span> permettraient à un attaquant d'effectuer une\nélévation de privilèges.\n",
  "title": "Vulnérabilités sur CA firewall",
  "vendor_advisories": [
    {
      "published_at": null,
      "title": "Bulletin de sécurité 34818 de CA du 22 janvier 2007",
      "url": null
    }
  ]
}