{
  "$ref": "https://www.cert.ssi.gouv.fr/openapi.json",
  "affected_systems": [
    {
      "description": "versions antérieures à SPIP 2.0.23",
      "product": {
        "name": "SPIP",
        "vendor": {
          "name": "SPIP",
          "scada": false
        }
      }
    },
    {
      "description": "Versions antérieures à SPIP 3.0.9",
      "product": {
        "name": "SPIP",
        "vendor": {
          "name": "SPIP",
          "scada": false
        }
      }
    },
    {
      "description": "versions antérieures à SPIP 2.1.22",
      "product": {
        "name": "SPIP",
        "vendor": {
          "name": "SPIP",
          "scada": false
        }
      }
    }
  ],
  "affected_systems_content": null,
  "content": "## Solution\n\nSe référer au bulletin de sécurité de l'éditeur pour l'obtention des\ncorrectifs (cf. section Documentation).\n",
  "cves": [],
  "links": [
    {
      "title": "Changements entre la version 2.1.21 et 2.1.22",
      "url": "http://www.spip.net/fr_article5620.html"
    },
    {
      "title": "Changements entre la version 2.0.22 et 2.0.23",
      "url": "http://www.spip.net/fr_article5621.html"
    },
    {
      "title": "Changements entre la version 3.0.8 et 3.0.9",
      "url": "http://www.spip.net/fr_article5619.html"
    }
  ],
  "reference": "CERTA-2013-AVI-329",
  "revisions": [
    {
      "description": "version initiale.",
      "revision_date": "2013-05-28T00:00:00.000000"
    }
  ],
  "risks": [
    {
      "description": "Élévation de privilèges"
    }
  ],
  "summary": "Une vulnérabilité a été corrigée dans <span class=\"textit\">SPIP</span>.\nElle permet à un attaquant de provoquer une élévation de privilèges.\n",
  "title": "Vulnérabilité dans SPIP",
  "vendor_advisories": [
    {
      "published_at": null,
      "title": "Bulletin de sécurité SPIP du 24 mai 2013",
      "url": "http://www.spip.net/fr_article4200.html"
    }
  ]
}