{
  "$ref": "https://www.cert.ssi.gouv.fr/openapi.json",
  "affected_systems": [],
  "affected_systems_content": "<p>Cisco IOS 12.  <P><SPAN class=\"textit\">pour de plus amples informations, se  référer aux bulletins de sécurité de l'éditeur (cf. section  Documentation).</SPAN></P></p>",
  "content": "## Description\n\nNeuf vulnérabilités ont été découvertes dans le système Cisco IOS. Ces\nvulnérabilités touchent de nombreuses parties du système et, pour la\nplupart, permettent à un utilisateur malintentionné de réaliser un déni\nde service.\n\nPour le détail complet des vulnérabilités, se référer aux bulletins de\nsécurité de l'éditeur (cf. section Documentation).\n\n## Solution\n\nSe référer aux bulletins de sécurité de l'éditeur pour l'obtention des\ncorrectifs (cf. section Documentation).\n",
  "cves": [],
  "links": [
    {
      "title": "Bulletin de sécurité Cisco 20090923-sip du 23 septembre    2009 :",
      "url": "http://www.cisco.com/warp/public/707/cisco-sa-20090923-sip.shtml"
    },
    {
      "title": "Bulletin de sécurité Cisco 20090923-auth-proy du 23    septembre 2009 :",
      "url": "http://www.cisco.com/warp/public/707/cisco-sa-20090923-auth-proy.shtml"
    },
    {
      "title": "Bulletin de sécurité Cisco 20090923-ntp du 23 septembre    2009 :",
      "url": "http://www.cisco.com/warp/public/707/cisco-sa-20090923-ntp.shtml"
    },
    {
      "title": "Bulletin de sécurité Cisco 20090923-ipsec du 23 septembre    2009 :",
      "url": "http://www.cisco.com/warp/public/707/cisco-sa-20090923-ipsec.shtml"
    },
    {
      "title": "Bulletin de sécurité Cisco 20090923-h323 du 23 septembre    2009 :",
      "url": "http://www.cisco.com/warp/public/707/cisco-sa-20090923-h323.shtml"
    },
    {
      "title": "Bulletin de sécurité Cisco 20090923-acl du 23 septembre    2009 :",
      "url": "http://www.cisco.com/warp/public/707/cisco-sa-20090923-acl.shtml"
    },
    {
      "title": "Bulletin de sécurité Cisco 20090923-ios-fw du 23 septembre    2009 :",
      "url": "http://www.cisco.com/warp/public/707/cisco-sa-20090923-ios-fw.shtml"
    },
    {
      "title": "Bulletin de sécurité Cisco 20090923-tunnels du 23 septembre    2009 :",
      "url": "http://www.cisco.com/warp/public/707/cisco-sa-20090923-tunnels.shtml"
    },
    {
      "title": "Bulletin de sécurité Cisco 20090923-tls du 23 septembre    2009 :",
      "url": "http://www.cisco.com/warp/public/707/cisco-sa-20090923-tls.shtml"
    }
  ],
  "reference": "CERTA-2009-AVI-402",
  "revisions": [
    {
      "description": "version initiale.",
      "revision_date": "2009-09-24T00:00:00.000000"
    }
  ],
  "risks": [
    {
      "description": "Déni de service à distance"
    },
    {
      "description": "Déni de service"
    },
    {
      "description": "Contournement de la politique de sécurité"
    },
    {
      "description": "Atteinte à la confidentialité des données"
    }
  ],
  "summary": "De multiples vulnérabilités ont été découvertes dans le système <span\nclass=\"textit\">Cisco IOS</span>. L'exploitation de ces vulnérabilités\npermet de contourner la politique de sécurité, de porter atteinte à la\nconfidentialité des données, ou de réaliser un déni de service à\ndistance.\n",
  "title": "Multiples vulnérabilités dans Cisco IOS",
  "vendor_advisories": [
    {
      "published_at": null,
      "title": "Bulletins de sécurité Cisco IOS du 23 septembre 2009",
      "url": null
    }
  ]
}