{
  "$ref": "https://www.cert.ssi.gouv.fr/openapi.json",
  "affected_systems": [],
  "affected_systems_content": "<p>DokuWiki, version 2009-12-25 et  versions antérieures.</p>",
  "content": "## Description\n\nDeux vulnérabilités de DokuWiki ont été publiées :\n\n-   la première autorise tout utilisateur à lister tous les fichiers\n    présents sur le serveurs. Une preuve de faisabilité est présente sur\n    l'Internet ;\n-   la seconde permet à un utilisateur malveillant de modifier les\n    règles de contrôle d'accès en vigueur sur le serveur.\n\n## Solution\n\nLa version 2009-12-25<span class=\"textbf\">c</span> remédie à ces\nproblèmes.\n\nSe référer au bulletin de sécurité de l'éditeur pour l'obtention des\ncorrectifs (cf. section Documentation).\n",
  "cves": [],
  "links": [
    {
      "title": "Site de téléchargement du projet DokuWiki :",
      "url": "http://www.dokuwiki.org/"
    }
  ],
  "reference": "CERTA-2010-AVI-057",
  "revisions": [
    {
      "description": "version initiale.",
      "revision_date": "2010-02-08T00:00:00.000000"
    }
  ],
  "risks": [
    {
      "description": "Contournement de la politique de sécurité"
    }
  ],
  "summary": "Des vulnérabilités de DokuWiki permettent le contournement de la\npolitique de sécurité.\n",
  "title": "Vulnérabilités de DokuWiki",
  "vendor_advisories": [
    {
      "published_at": null,
      "title": "Bulletin de version DokuWiki 2009-12-25c",
      "url": "http://www.dokuwiki.org/changes"
    }
  ]
}