{
  "$ref": "https://www.cert.ssi.gouv.fr/openapi.json",
  "affected_systems": [
    {
      "description": "Drupal core 7.x versions antérieures à 7.44",
      "product": {
        "name": "Drupal",
        "vendor": {
          "name": "Drupal",
          "scada": false
        }
      }
    },
    {
      "description": "Drupal core 8.x versions antérieures à 8.1.3",
      "product": {
        "name": "Drupal",
        "vendor": {
          "name": "Drupal",
          "scada": false
        }
      }
    }
  ],
  "affected_systems_content": null,
  "content": "## Solution\n\nSe référer au bulletin de sécurité de l'éditeur pour l'obtention des\ncorrectifs (cf. section Documentation).\n",
  "cves": [],
  "links": [
    {
      "title": "Bulletin de sécurité Drupal SA-CORE-2016-002 du 15 juin    2016",
      "url": "https://www.drupal.org/SA-CORE-2016-002"
    }
  ],
  "reference": "CERTFR-2016-AVI-210",
  "revisions": [
    {
      "description": "version initiale.",
      "revision_date": "2016-06-16T00:00:00.000000"
    }
  ],
  "risks": [
    {
      "description": "Contournement de la politique de sécurité"
    },
    {
      "description": "Élévation de privilèges"
    }
  ],
  "summary": "De multiples vulnérabilités ont été corrigées dans <span\nclass=\"textit\">Drupal Core</span>. Elles permettent à un attaquant de\nprovoquer un contournement de la politique de sécurité et une élévation\nde privilèges.\n",
  "title": "Multiples vulnérabilités dans Drupal Core",
  "vendor_advisories": [
    {
      "published_at": null,
      "title": "Bulletin de sécurité Drupal SA-CORE-2016-002 du 15 juin 2016",
      "url": null
    }
  ]
}