{
  "$ref": "https://www.cert.ssi.gouv.fr/openapi.json",
  "affected_systems": [],
  "affected_systems_content": "<p>OpenVPN versions antérieures à la  version 2.0.1.</p>",
  "content": "## Description\n\nOpenVPN est un logiciel libre permettant de créer des réseaux privés\nvirtuels SSL.  \nPlusieurs vulnérabilités dans OpenVPN permettent à un utilisateur mal\nintentionné de réaliser un déni de service sur la plate-forme\nvulnérable.\n\n## Solution\n\nMettre à jour OpenVPN en version 2.0.1 ou versions supérieures.  \nSe référer au bulletin de sécurité de l'éditeur pour l'obtention des\ncorrectifs (cf. section Documentation).\n",
  "cves": [],
  "links": [
    {
      "title": "Bulletin de sécurité OpenBSD pour OpenVPN du 23 août 2005 :",
      "url": "http://www.vuxml.org/openbsd/pkg-openvpn.html"
    },
    {
      "title": "Site Internet de OpenVPN :",
      "url": "http://openvpn.net"
    },
    {
      "title": "Liste des changements de OpenVPN :",
      "url": "http://openvpn.net/changelog.html"
    },
    {
      "title": "Bulletin de sécurité Debian DSA-851 du 09 octobre 2005 :",
      "url": "http://www.debian.org/security/2005/dsa-851"
    },
    {
      "title": "Bulletin de sécurité SUSE SUSE-SR:2005:020 du 12 septembre    2005 :",
      "url": "http://www.novell.com/linux/security/advisories/2005_20_sr.html"
    },
    {
      "title": "Bulletin de sécurité Mandriva MDKSA-2005:145 du 22 août    2005 :",
      "url": "http://www.mandriva.com/security/advisories?name=MDKSA-2005:145"
    }
  ],
  "reference": "CERTA-2005-AVI-335",
  "revisions": [
    {
      "description": "version initiale.",
      "revision_date": "2005-09-06T00:00:00.000000"
    },
    {
      "description": "ajout de la référence au bulletin de sécurité SUSE.",
      "revision_date": "2005-09-14T00:00:00.000000"
    },
    {
      "description": "ajout de la référence au bulletin de sécurité Debian DSA-851.",
      "revision_date": "2005-10-10T00:00:00.000000"
    }
  ],
  "risks": [
    {
      "description": "Déni de service"
    }
  ],
  "summary": null,
  "title": "Vulnérabilité de OpenVPN",
  "vendor_advisories": [
    {
      "published_at": null,
      "title": "Bulletin de sécurité Mandriva MDKSA-2005:145 du 22 août 2005",
      "url": null
    }
  ]
}