{
  "$ref": "https://www.cert.ssi.gouv.fr/openapi.json",
  "affected_systems": [],
  "affected_systems_content": "<p>Squid versions 2.5.STABLE10 et  antérieures.</p>",
  "content": "## Description\n\nUne erreur dans la mise en œuvre dans Squid de l'authentification\nutilisant le protocole de Microsoft : NTLM (NT Lan Manager) permet à un\nutilisateur distant mal intentionné de provoquer un déni de service sur\nle système vulnérable par le biais d'une requête malicieusement\nconstituée.\n\n## Solution\n\nSe référer aux bulletins de sécurité des éditeurs pour l'obtention de\ncorrectifs (cf. Documentation).\n",
  "cves": [],
  "links": [
    {
      "title": "Bulletin de sécurité Ubuntu USN-192-1 du 30 septembre 2005    :",
      "url": "http://www.ubuntu.com/usn/usn-192-1"
    },
    {
      "title": "Bulletin de sécurité Mandriva MDKSA-2005:181 du 11 octobre    2005 :",
      "url": "http://www.mandriva.com/security/advisories?name=MDKSA-2005:181"
    },
    {
      "title": "Bulletin de sécurité Debian DSA-828 du 30 septembre 2005 :",
      "url": "http://www.debian.org/security/2005/dsa-828"
    },
    {
      "title": "Bulletin de sécurité RedHat RHSA-2006-0052 du 07 mars 2006    :",
      "url": "https://rhn.redhat.com/errata/RHSA-2006-0052.html"
    }
  ],
  "reference": "CERTA-2005-AVI-371",
  "revisions": [
    {
      "description": "ajout de la référence au bulletin de sécurité RedHat.",
      "revision_date": "2005-03-08T00:00:00.000000"
    },
    {
      "description": "version initiale.",
      "revision_date": "2005-10-03T00:00:00.000000"
    },
    {
      "description": "ajout de la référence au bulletin de sécurité Mandriva MDKSA-2005:181.",
      "revision_date": "2005-10-12T00:00:00.000000"
    }
  ],
  "risks": [
    {
      "description": "Déni de service"
    }
  ],
  "summary": "Une vulnérabilité dans Squid permet à un utilisateur distant mal\nintentionné de provoquer un déni de service.\n",
  "title": "Vulnérabilité de Squid",
  "vendor_advisories": [
    {
      "published_at": null,
      "title": "Rapport d'erreur Squid Bugzilla #1391 du 15 septembre 2005",
      "url": "http://www.squid-cache.org/bugs/show_bug.cgi?id=1391"
    }
  ]
}