{
  "$ref": "https://www.cert.ssi.gouv.fr/openapi.json",
  "affected_systems": [
    {
      "description": "Windows XP",
      "product": {
        "name": "Windows",
        "vendor": {
          "name": "Microsoft",
          "scada": false
        }
      }
    },
    {
      "description": "Windows Server 2003 R2",
      "product": {
        "name": "Windows",
        "vendor": {
          "name": "Microsoft",
          "scada": false
        }
      }
    },
    {
      "description": "Windows Server 2003",
      "product": {
        "name": "Windows",
        "vendor": {
          "name": "Microsoft",
          "scada": false
        }
      }
    },
    {
      "description": "Windows Vista",
      "product": {
        "name": "Windows",
        "vendor": {
          "name": "Microsoft",
          "scada": false
        }
      }
    },
    {
      "description": "Windows 8",
      "product": {
        "name": "Windows",
        "vendor": {
          "name": "Microsoft",
          "scada": false
        }
      }
    }
  ],
  "affected_systems_content": null,
  "content": "## Solution\n\nSe référer au bulletin de sécurité de l'éditeur pour l'obtention des\ncorrectifs (cf. section Documentation).\n",
  "cves": [],
  "links": [
    {
      "title": "Annonce Microsoft",
      "url": "https://blogs.technet.microsoft.com/msrc/2017/04/14/protecting-customers-and-evaluating-risk/"
    }
  ],
  "reference": "CERTFR-2017-AVI-181",
  "revisions": [
    {
      "description": "version initiale.",
      "revision_date": "2017-06-14T00:00:00.000000"
    }
  ],
  "risks": [
    {
      "description": "Exécution de code arbitraire à distance"
    }
  ],
  "summary": "De multiples vulnérabilités ont été corrigées dans <span\nclass=\"textit\">les systèmes d'exploitation Microsoft Windows\nobsolètes</span>. Elles permettent à un attaquant de provoquer une\nexécution de code arbitraire à distance.\n",
  "title": "Multiples vulnérabilités dans les systèmes d'exploitation Microsoft Windows obsolètes",
  "vendor_advisories": [
    {
      "published_at": null,
      "title": "Bulletin de sécurité Windows du 13 juin 2017",
      "url": "https://blogs.technet.microsoft.com/msrc/2017/06/13/june-2017-security-update-release/"
    },
    {
      "published_at": null,
      "title": "Bulletin de sécurité Windows 4025685 du 13 juin 2017",
      "url": "https://support.microsoft.com/en-us/help/4025687/microsoft-security-advisory-4025685-guidance-for-older-platforms"
    }
  ]
}