{
  "$ref": "https://www.cert.ssi.gouv.fr/openapi.json",
  "affected_systems": [],
  "affected_systems_content": "<P>PERL WIN32 versions 5.8.3 et antérieures.</P>",
  "content": "## Description\n\nL'envoi d'une requête HTTP judicieusement composée vers un serveur\nutilisant la fonction win32_stat permet, par le biais d'un débordement\nde mémoire, d'exécuter du code arbitraire à distance.\n\n## Solution\n\n-   La version 5.8.4 de PERL corrigera cette vulnérabilité ;\n\n-   Correctif pour la version PERL 5.8.x :\n\n        http://public.activestate.com/cgi-bin/perlbrowse?patch=22552\n\n-   Correctif pour la version PERL 5.9.x en développement :\n\n        http://public.activestate.com/cgi-bin/perlbrowse?patch=22466\n",
  "cves": [],
  "links": [
    {
      "title": "Bulletin de sécurité de iDEFENSE 04.05.04 :",
      "url": "http://www.idefense.com/application/poi/display?id=93&type=vulnerabilities"
    }
  ],
  "reference": "CERTA-2004-AVI-114",
  "revisions": [
    {
      "description": "version initiale.",
      "revision_date": "2004-04-08T00:00:00.000000"
    }
  ],
  "risks": [
    {
      "description": "Exécution de code arbitraire à distance"
    }
  ],
  "summary": "Une vulnérabilité dans la fonction win32_stat de PERL WIN32 permet à un\nutilisateur distant mal intentionné d'exécuter du code arbitraire sur la\nmachine cible.\n",
  "title": "Vulnérabilité dans PERL WIN32",
  "vendor_advisories": [
    {
      "published_at": null,
      "title": "Bulletin de sécurité iDEFENSE",
      "url": null
    }
  ]
}