{
  "$ref": "https://www.cert.ssi.gouv.fr/openapi.json",
  "affected_systems": [
    {
      "description": "Huawei HiLink E3276",
      "product": {
        "name": "N/A",
        "vendor": {
          "name": "N/A",
          "scada": false
        }
      }
    },
    {
      "description": "Huawei HiLink E3236",
      "product": {
        "name": "N/A",
        "vendor": {
          "name": "N/A",
          "scada": false
        }
      }
    }
  ],
  "affected_systems_content": null,
  "content": "## Solution\n\nSe référer au bulletin de sécurité de l'éditeur pour l'obtention des\ncorrectifs (cf. section Documentation).\n",
  "cves": [],
  "links": [
    {
      "title": "Bulletin de sécurité Huawei Huawei-SA-20140806-01-HiLink du    06 août 2014",
      "url": "http://www.huawei.com/en/security/psirt/security-bulletins/security-advisories/hw-360246.htm"
    }
  ],
  "reference": "CERTFR-2014-AVI-340",
  "revisions": [
    {
      "description": "version initiale.",
      "revision_date": "2014-08-07T00:00:00.000000"
    }
  ],
  "risks": [
    {
      "description": "Injection de requêtes illégitimes par rebond (CSRF)"
    }
  ],
  "summary": "Une vulnérabilité a été corrigée dans <span class=\"textit\">Huawei\nHiLink</span>. Elle permet à un attaquant de provoquer une injection de\nrequêtes illégitimes par rebond (CSRF).\n",
  "title": "Vulnérabilité dans Huawei HiLink",
  "vendor_advisories": [
    {
      "published_at": null,
      "title": "Bulletin de sécurité Huawei Huawei-SA-20140806-01-HiLink du 06 août 2014",
      "url": null
    }
  ]
}